heiplanet_models/Jmodel.py
heiplanet_models/__init__.py
heiplanet_models/computation_graph.py
heiplanet_models/config_Jmodel.json
heiplanet_models/utils.py
heiplanet_models-0.1.2.dist-info/METADATA
heiplanet_models-0.1.2.dist-info/WHEEL
heiplanet_models-0.1.2.dist-info/licenses/LICENSE
heiplanet_models-0.1.2.dist-info/RECORD
