Metadata-Version: 2.4
Name: heiplanet-models
Version: 0.1.2
Summary: Model backend for the HeiPlanet project
Project-URL: Homepage, https://github.com/ssciwr/onehealth-model-backend
Project-URL: Issues, https://github.com/ssciwr/onehealth-model-backend/issues
Author-email: Scientific Software Center <ssc@uni-heidelberg.de>
License: MIT License
License-File: LICENSE
Classifier: License :: OSI Approved :: MIT License
Classifier: Operating System :: OS Independent
Classifier: Programming Language :: Python :: 3
Requires-Python: >=3.9
Requires-Dist: dask
Requires-Dist: geopandas[all]
Requires-Dist: matplotlib
Requires-Dist: netcdf4
Requires-Dist: numpy
Requires-Dist: rioxarray
Requires-Dist: xarray[parallel]
Provides-Extra: dev
Requires-Dist: graphviz; extra == 'dev'
Requires-Dist: pre-commit; extra == 'dev'
Requires-Dist: pytest; extra == 'dev'
Requires-Dist: pytest-cov; extra == 'dev'
Provides-Extra: viz
Requires-Dist: graphviz; extra == 'viz'
